bytewax-0.21.1.dist-info/METADATA
bytewax-0.21.1.dist-info/WHEEL
bytewax-0.21.1.dist-info/licenses/LICENSE
bytewax/outputs.py
bytewax/connectors/kafka/operators.py
bytewax/connectors/kafka/__init__.py
bytewax/connectors/kafka/serde.py
bytewax/connectors/demo.py
bytewax/connectors/stdio.py
bytewax/connectors/__init__.py
bytewax/connectors/files.py
bytewax/errors.py
bytewax/py.typed
bytewax/visualize.py
bytewax/dataflow.py
bytewax/_utils.py
bytewax/tracing.py
bytewax/inputs.py
bytewax/_bytewax.pyi
bytewax/testing.py
bytewax/_metrics.py
bytewax/run.py
bytewax/recovery.py
bytewax/operators/windowing.py
bytewax/operators/helpers.py
bytewax/operators/__init__.py
bytewax/_bytewax.cpython-39-aarch64-linux-gnu.so
bytewax-0.21.1.dist-info/RECORD
