Metadata-Version: 2.3
Name: bytewax
Version: 0.21.1
Classifier: Development Status :: 4 - Beta
Classifier: Intended Audience :: Developers
Classifier: Operating System :: OS Independent
Classifier: Programming Language :: Rust
Classifier: Programming Language :: Python :: Implementation :: CPython
Classifier: Programming Language :: Python :: Implementation :: PyPy
Classifier: Programming Language :: Python :: 3
Classifier: Programming Language :: Python :: 3.8
Classifier: Programming Language :: Python :: 3.9
Classifier: Programming Language :: Python :: 3.10
Classifier: Programming Language :: Python :: 3.11
Classifier: Programming Language :: Python :: 3.12
Classifier: Topic :: System :: Networking
Classifier: Topic :: System :: Distributed Computing
Requires-Dist: typing-extensions >=4
Requires-Dist: prometheus-client >=0.18
Requires-Dist: requests >=2.0 ; extra == 'kafka'
Requires-Dist: fastavro >=1.8 ; extra == 'kafka'
Requires-Dist: confluent-kafka >=2.0.2 ; extra == 'kafka'
Provides-Extra: kafka
License-File: LICENSE
Requires-Python: >=3.8
Project-URL: Source Code, https://github.com/bytewax/bytewax
Project-URL: Issues, https://github.com/bytewax/bytewax/issues
Project-URL: Documentation, https://docs.bytewax.io/
Project-URL: Changelog, https://github.com/bytewax/bytewax/blob/main/CHANGELOG.md
